tweetfeels/__init__.py
tweetfeels/tweetdata.py
tweetfeels/tweetfeels.py
tweetfeels/tweetlistener.py
tweetfeels/utils.py
tweetfeels/version.py
tweetfeels-0.4.1.dist-info/LICENSE
tweetfeels-0.4.1.dist-info/METADATA
tweetfeels-0.4.1.dist-info/WHEEL
tweetfeels-0.4.1.dist-info/top_level.txt
tweetfeels-0.4.1.dist-info/RECORD
